LICENSE.txt
MANIFEST.in
README.rst
setup.py
ratelimit/__init__.py
ratelimit/decorator.py
ratelimit/exception.py
ratelimit.egg-info/PKG-INFO
ratelimit.egg-info/SOURCES.txt
ratelimit.egg-info/dependency_links.txt
ratelimit.egg-info/not-zip-safe
ratelimit.egg-info/top_level.txt