Metadata-Version: 1.1
Name: ratelimit
Version: 2.0.0
Summary: API rate limit decorator
Home-page: https://github.com/tomasbasham/ratelimit
Author: Tomas Basham
Author-email: me@tomasbasham.co.uk
License: MIT
Keywords: ratelimit,api,decorator
Platform: UNKNOWN
Classifier: Development Status :: 5 - Production/Stable
Classifier: Intended Audience :: Developers
Classifier: License :: OSI Approved :: MIT License
Classifier: Natural Language :: English
Classifier: Programming Language :: Python
Classifier: Topic :: Software Development
